{"prepare_queue":{"installed":[],"uninstalled":[]},"config_munge":{"res/xml/config.xml":{"/*":{"<feature name=\"SplashScreen\"><param name=\"android-package\" value=\"org.apache.cordova.splashscreen.SplashScreen\" /></feature>":1,"<feature name=\"PushNotification\"><param name=\"android-package\" onload=\"true\" value=\"com.pushwoosh.plugin.pushnotifications.PushNotifications\" /></feature>":1,"<feature name=\"WebIntent\"><param name=\"android-package\" value=\"net.tunts.webintent.WebIntent\" /></feature>":1}},"AndroidManifest.xml":{"/manifest":{"<uses-permission android:name=\"android.permission.ACCESS_NETWORK_STATE\" />":1,"<uses-permission android:name=\"android.permission.GET_ACCOUNTS\" />":1,"<uses-permission android:name=\"android.permission.WAKE_LOCK\" />":1,"<uses-permission android:name=\"com.google.android.c2dm.permission.RECEIVE\" />":1,"<permission android:name=\"org.brewingupacure.buacmobile.permission.C2D_MESSAGE\" android:protectionLevel=\"signature\" />":1,"<uses-permission android:name=\"org.brewingupacure.buacmobile.permission.C2D_MESSAGE\" />":1,"<uses-permission android:name=\"android.permission.READ_PHONE_STATE\" />":1,"<uses-permission android:name=\"android.permission.INTERNET\" />":1},"/*/application/activity":{},"/manifest/application":{"<activity android:name=\"com.arellomobile.android.push.PushWebview\" />":1,"<activity android:name=\"com.arellomobile.android.push.MessageActivity\" />":1,"<activity android:name=\"com.arellomobile.android.push.PushHandlerActivity\" />":1,"<activity android:label=\"@string/app_name\" android:name=\"com.facebook.LoginActivity\" />":1,"<receiver android:name=\"com.google.android.gcm.GCMBroadcastReceiver\" android:permission=\"com.google.android.c2dm.permission.SEND\"><intent-filter><action android:name=\"com.google.android.c2dm.intent.RECEIVE\" /><action android:name=\"com.google.android.c2dm.intent.REGISTRATION\" /><category android:name=\"org.brewingupacure.buacmobile\" /></intent-filter></receiver>":1,"<service android:name=\"com.arellomobile.android.push.PushGCMIntentService\" />":1,"<service android:name=\"com.arellomobile.android.push.GeoLocationService\" />":1,"<receiver android:name=\"com.arellomobile.android.push.AlarmReceiver\" />":1},"/manifest/application/activity":{"<intent-filter><action android:name=\"org.brewingupacure.buacmobile.MESSAGE\" /><category android:name=\"android.intent.category.DEFAULT\" /></intent-filter>":1}},"undefined":{"undefined":{"<access origin=\"*.pushwoosh.com\" />":1}}},"installed_plugins":{"org.apache.cordova.splashscreen":{"PACKAGE_NAME":"org.brewingupacure.buacmobile"},"com.pushwoosh.plugins.pushwoosh":{"PACKAGE_NAME":"org.brewingupacure.buacmobile"},"net.tunts.webintent":{"PACKAGE_NAME":"org.brewingupacure.buacmobile"}},"dependent_plugins":{}}